cloud_diffusion/__init__.py
cloud_diffusion/dataset.py
cloud_diffusion/ddpm.py
cloud_diffusion/models.py
cloud_diffusion/simple_diffusion.py
cloud_diffusion/utils.py
cloud_diffusion/version.py
cloud_diffusion/wandb.py
cloud_diffusion-0.5.1.dist-info/METADATA
cloud_diffusion-0.5.1.dist-info/WHEEL
cloud_diffusion-0.5.1.dist-info/top_level.txt
cloud_diffusion-0.5.1.dist-info/RECORD
