Metadata-Version: 2.1
Name: cloud-diffusion
Version: 0.5.1
Summary: Diffusion on the Clouds: Short-term solar energy forecasting with Diffusion Models
Home-page: https://github.com/tcapelle/cloud_diffusion
Author: Thomas Capelle
Author-email: tcapelle@pm.me
License: MIT
Keywords: artificial intelligence,generative models,pytorch,stable diffusion
Classifier: Development Status :: 4 - Beta
Classifier: Intended Audience :: Developers
Classifier: Topic :: Scientific/Engineering :: Artificial Intelligence
Classifier: License :: OSI Approved :: MIT License
Classifier: Programming Language :: Python :: 3.10
Requires-Dist: torch
Requires-Dist: fastprogress
Requires-Dist: fastcore
Requires-Dist: wandb
Requires-Dist: numpy
Requires-Dist: matplotlib
Requires-Dist: diffusers
Requires-Dist: denoising-diffusion-pytorch
